napari_obj/__init__.py
napari_obj/_reader.py
napari_obj/napari.yaml
napari_obj/_tests/__init__.py
napari_obj/_tests/test_reader.py
napari_obj-1.0.0.dist-info/LICENSE
napari_obj-1.0.0.dist-info/METADATA
napari_obj-1.0.0.dist-info/WHEEL
napari_obj-1.0.0.dist-info/entry_points.txt
napari_obj-1.0.0.dist-info/top_level.txt
napari_obj-1.0.0.dist-info/RECORD
