Metadata-Version: 2.1
Name: napari-obj
Version: 1.0.0
Summary: A plugin to read .obj files
Home-page: https://github.com/guignardlab/napari-obj
Author: Léo Guignard
Author-email: leo.guignard@univ-amu.fr
License: MIT
Project-URL: Bug Tracker, https://github.com/guignardlab/napari-obj/issues
Project-URL: Documentation, https://github.com/guignardlab/napari-obj#README.md
Project-URL: Source Code, https://github.com/guignardlab/napari-obj
Project-URL: User Support, https://github.com/guignardlab/napari-obj/issues
Classifier: Development Status :: 4 - Beta
Classifier: Framework :: napari
Classifier: Intended Audience :: Developers
Classifier: License :: OSI Approved :: MIT License
Classifier: Operating System :: OS Independent
Classifier: Programming Language :: Python
Classifier: Programming Language :: Python :: 3
Classifier: Programming Language :: Python :: 3 :: Only
Classifier: Programming Language :: Python :: 3.8
Classifier: Programming Language :: Python :: 3.9
Classifier: Programming Language :: Python :: 3.10
Classifier: Topic :: Scientific/Engineering :: Image Processing
Requires-Python: >=3.8
License-File: LICENSE
Requires-Dist: numpy
Provides-Extra: testing
Requires-Dist: tox ; extra == 'testing'
Requires-Dist: pytest ; extra == 'testing'
Requires-Dist: pytest-cov ; extra == 'testing'
